aws_profiles/__init__.py
aws_profiles/exceptions.py
aws_profiles/profile.py
metric_system/AWSPublisher.md
metric_system/__init__.py
metric_system/functions/__init__.py
metric_system/functions/aws_metric_publisher.py
metric_system/functions/exceptions.py
metric_system/functions/file_metric_publisher.py
metric_system/functions/metric.py
metric_system/functions/metric_publisher.py
metric_system/functions/metrics.py
switcheroo/__init__.py
switcheroo/base/__init__.py
switcheroo/base/data_store/__init__.py
switcheroo/base/data_store/exceptions.py
switcheroo/base/data_store/s3.py
switcheroo/base/exceptions/s3.py
switcheroo/base/scripts/configure.py
switcheroo/base/serializer.py
switcheroo/paths.py
switcheroo/ssh/__init__.py
switcheroo/ssh/data_org/__init__.py
switcheroo/ssh/data_org/publisher/__init__.py
switcheroo/ssh/data_org/publisher/s3.py
switcheroo/ssh/data_org/retriever/__init__.py
switcheroo/ssh/data_org/retriever/s3.py
switcheroo/ssh/data_stores/__init__.py
switcheroo/ssh/exceptions.py
switcheroo/ssh/objects/__init__.py
switcheroo/ssh/objects/key.py
switcheroo/ssh/scripts/__init__.py
switcheroo/ssh/scripts/publish.py
switcheroo/ssh/scripts/retrieve.py
switcheroo/util.py
key_switcheroo-1.0.2.dist-info/METADATA
key_switcheroo-1.0.2.dist-info/WHEEL
key_switcheroo-1.0.2.dist-info/entry_points.txt
key_switcheroo-1.0.2.dist-info/RECORD
