Metadata-Version: 2.1
Name: key-switcheroo
Version: 1.0.2
Summary: Rotate SSH keys, stored in the cloud!
Author: Your Name
Author-email: you@example.com
Requires-Python: >=3.11,<4.0
Classifier: Programming Language :: Python :: 3
Classifier: Programming Language :: Python :: 3.11
Requires-Dist: boto3 (>=1.27.0,<2.0.0)
Requires-Dist: boto3-stubs[cloudwatch,s3,sts] (==1.28.2)
Requires-Dist: pycryptodome (>=3.18.0,<4.0.0)
